MANIFEST.in
setup.cfg
setup.py
kernelhive/__init__.py
kernelhive/connectivity.py
kernelhive/management.py
kernelhive/monitoring.py
kernelhive/serving.py
kernelhive/utils.py
kernelhive.egg-info/PKG-INFO
kernelhive.egg-info/SOURCES.txt
kernelhive.egg-info/dependency_links.txt
kernelhive.egg-info/requires.txt
kernelhive.egg-info/top_level.txt
kernelhive/managers/ProcessEnforcer.py
kernelhive/managers/__init__.py
kernelhive/monitoring_handlers/PrintingHandler.py
kernelhive/monitoring_handlers/__init__.py
kernelhive/monitors/GPUMonitor.py
kernelhive/monitors/ProcessMonitor.py
kernelhive/monitors/__init__.py
kernelhive/scripts/add_node.sh
kernelhive/scripts/call_service.sh
kernelhive/scripts/get_infrastructure.sh
kernelhive/scripts/process_enforcer/add_process.sh
kernelhive/static/handlebars.min-v4.0.10.js
kernelhive/static/process_enforcer.html